odoo8_addon_cron_run_manually-8.0.1.0.0.99.dev7-py2.7-nspkg.pth
odoo8_addon_cron_run_manually-8.0.1.0.0.99.dev7.dist-info/DESCRIPTION.rst
odoo8_addon_cron_run_manually-8.0.1.0.0.99.dev7.dist-info/METADATA
odoo8_addon_cron_run_manually-8.0.1.0.0.99.dev7.dist-info/RECORD
odoo8_addon_cron_run_manually-8.0.1.0.0.99.dev7.dist-info/WHEEL
odoo8_addon_cron_run_manually-8.0.1.0.0.99.dev7.dist-info/metadata.json
odoo8_addon_cron_run_manually-8.0.1.0.0.99.dev7.dist-info/namespace_packages.txt
odoo8_addon_cron_run_manually-8.0.1.0.0.99.dev7.dist-info/top_level.txt
odoo_addons/cron_run_manually/__init__.py
odoo_addons/cron_run_manually/__openerp__.py
odoo_addons/cron_run_manually/ir_cron.py
odoo_addons/cron_run_manually/i18n/cron_run_manually.pot
odoo_addons/cron_run_manually/i18n/de.po
odoo_addons/cron_run_manually/i18n/es.po
odoo_addons/cron_run_manually/i18n/fr.po
odoo_addons/cron_run_manually/i18n/it.po
odoo_addons/cron_run_manually/i18n/nl.po
odoo_addons/cron_run_manually/i18n/pt_BR.po
odoo_addons/cron_run_manually/i18n/sl.po
odoo_addons/cron_run_manually/i18n/tr.po
odoo_addons/cron_run_manually/static/description/icon.png
odoo_addons/cron_run_manually/tests/correct_uid.yml
odoo_addons/cron_run_manually/view/ir_cron.xml
